README.txt
setup.cfg
setup.py
getpaid/__init__.py
getpaid.verkkomaksut.egg-info/PKG-INFO
getpaid.verkkomaksut.egg-info/SOURCES.txt
getpaid.verkkomaksut.egg-info/dependency_links.txt
getpaid.verkkomaksut.egg-info/entry_points.txt
getpaid.verkkomaksut.egg-info/namespace_packages.txt
getpaid.verkkomaksut.egg-info/not-zip-safe
getpaid.verkkomaksut.egg-info/paster_plugins.txt
getpaid.verkkomaksut.egg-info/requires.txt
getpaid.verkkomaksut.egg-info/top_level.txt
getpaid/verkkomaksut/__init__.py
getpaid/verkkomaksut/interfaces.py
getpaid/verkkomaksut/adapters/__init__.py
getpaid/verkkomaksut/adapters/options.py
getpaid/verkkomaksut/adapters/order.py
getpaid/verkkomaksut/adapters/verkkomaksut.py
getpaid/verkkomaksut/browser/__init__.py
getpaid/verkkomaksut/browser/admin.py
getpaid/verkkomaksut/browser/button.py
getpaid/verkkomaksut/browser/checkout.py
getpaid/verkkomaksut/tests/__init__.py
getpaid/verkkomaksut/tests/test_doctests.py
getpaid/verkkomaksut/utilities/__init__.py
getpaid/verkkomaksut/utilities/verkkomaksut_utilities.py