Metadata-Version: 1.0
Name: getpaid.verkkomaksut
Version: 0.1.1
Summary: Verkkomaksut payment processor for getpaid.
Home-page: http://pypi.python.org/pypi/getpaid.verkkomaksut
Author: Taito Horiuchi
Author-email: taito.horiuchi@gmail.com
License: GPL
Platform: UNKNOWN
Classifier: Framework :: Plone
Classifier: Programming Language :: Python
Classifier: Topic :: Software Development :: Libraries :: Python Modules
